litestar_svcs-0.1.2.dist-info/METADATA
litestar_svcs-0.1.2.dist-info/WHEEL
litestar_svcs/__init__.py
litestar_svcs/config.py
litestar_svcs/plugin.py
litestar_svcs/py.typed
litestar_svcs-0.1.2.dist-info/RECORD
