Metadata-Version: 2.1
Name: litestar-svcs
Version: 0.1.2
Summary: A plugin for Litestar to integrate `svcs`.
Author-Email: guacs <guacs.guacs@gmail.com>
License: MIT
Requires-Python: >=3.8
Requires-Dist: litestar>=2.0.0
Requires-Dist: svcs>=23.7.0
Requires-Dist: mypy>=1.7.0; extra == "lint"
Requires-Dist: ruff>=0.1.6; extra == "lint"
Requires-Dist: black>=23.11.0; extra == "lint"
Requires-Dist: pytest>=7.4.3; extra == "test"
Provides-Extra: lint
Provides-Extra: test
